smer_visual/__init__.py
smer_visual/smer.py
smer_visual/utils.py
smer_visual-1.1.1.dist-info/licenses/LICENSE
smer_visual-1.1.1.dist-info/METADATA
smer_visual-1.1.1.dist-info/WHEEL
smer_visual-1.1.1.dist-info/top_level.txt
smer_visual-1.1.1.dist-info/RECORD
