Metadata-Version: 2.4
Name: smer-visual
Version: 1.1.1
Summary: This package provides means of explainable classification of images with LLM-generated text descriptions, that are then analyzed using the Self Model Entities Related (SMER) explanation technique.
Author-email: Vojtěch Balek <vojta.balek@gmail.com>, Julija Jeršova <poty01@vse.cz>, Tomáš Kliegr <tomas.kliegr@vse.cz>, Michael Ahmet Ay <aymi00@vse.cz>
Project-URL: Homepage, https://github.com/vojtech-balek/SMERVisual
Project-URL: Bug Tracker, https://github.com/vojtech-balek/SMERVisual/issues
Requires-Python: >=3.10
License-File: LICENSE
Requires-Dist: opencv-python==4.11.0.86
Requires-Dist: matplotlib==3.9.2
Requires-Dist: numpy==1.26.4
Requires-Dist: pandas==2.2.3
Requires-Dist: Pillow==11.1.0
Requires-Dist: seaborn==0.13.2
Requires-Dist: scikit-learn==1.6.1
Requires-Dist: spacy==3.8.2
Requires-Dist: torch==2.4.1
Requires-Dist: tqdm==4.67.1
Requires-Dist: transformers==4.48.0
Requires-Dist: openai==1.52.2
Requires-Dist: lime==0.2.0.1
Dynamic: license-file
